congressapi
