Metadata-Version: 1.0
Name: congressapi
Version: 0.4
Summary: Wrapper for ProPublica Congress API
Home-page: http://github.com/kjchavez/congressapi
Author: Kevin Chavez
Author-email: kevin.j.chavez@gmail.com
License: MIT
Platform: UNKNOWN
